heapq.py
setup.py
micropython_heapq.egg-info/PKG-INFO
micropython_heapq.egg-info/SOURCES.txt
micropython_heapq.egg-info/dependency_links.txt
micropython_heapq.egg-info/top_level.txt