Metadata-Version: 1.0
Name: micropython-heapq
Version: 0.9.1
Summary: CPython heapq module ported to MicroPython
Home-page: https://github.com/micropython/micropython/issues/405
Author: MicroPython Developers
Author-email: micro-python@googlegroups.com
License: Python
Platform: UNKNOWN
